capsule_vacuum_vessel/__init__.py
capsule_vacuum_vessel/core.py
capsule_vacuum_vessel-0.0.2.dist-info/LICENSE
capsule_vacuum_vessel-0.0.2.dist-info/METADATA
capsule_vacuum_vessel-0.0.2.dist-info/WHEEL
capsule_vacuum_vessel-0.0.2.dist-info/top_level.txt
capsule_vacuum_vessel-0.0.2.dist-info/RECORD
